tryton_twilio.py
tryton_twilio-0.1.0.dist-info/LICENSE
tryton_twilio-0.1.0.dist-info/METADATA
tryton_twilio-0.1.0.dist-info/WHEEL
tryton_twilio-0.1.0.dist-info/top_level.txt
tryton_twilio-0.1.0.dist-info/RECORD
