Metadata-Version: 2.1
Name: tryton-twilio
Version: 0.1.0
Summary: Send SMS from Tryton via Twilio
Home-page: https://hg.b2ck.com/tryton-twilio
Author: B2CK
Author-email: info@b2ck.com
License: GPL-3
Keywords: tryton twilio SMS
Platform: Posix; MacOS X; Windows
Classifier: Framework :: Tryton
Classifier: Intended Audience :: Developers
Classifier: License :: OSI Approved :: GNU General Public License (GPL)
Classifier: Operating System :: OS Independent
Classifier: Programming Language :: Python :: 3
Classifier: Programming Language :: Python :: 3.5
Classifier: Programming Language :: Python :: 3.6
Classifier: Programming Language :: Python :: 3.6
Classifier: Programming Language :: Python :: 3.7
Classifier: Topic :: Internet
Classifier: Topic :: Software Development :: Libraries
Requires-Dist: twilio
Requires-Dist: trytond (>5.0)
